{
  "preRequisites:9": {
    "0:10": {
      "questIDHigh:4": -6812165720467355549,
      "questIDLow:4": -6511023184921807002
    },
    "1:10": {
      "questIDHigh:4": 3614039832860246671,
      "questIDLow:4": -8204155479287429298
    },
    "2:10": {
      "questIDHigh:4": -5188947688382772838,
      "questIDLow:4": -8955010384758446224
    },
    "3:10": {
      "questIDHigh:4": 5555739684431741358,
      "questIDLow:4": -8795107776831007617
    },
    "4:10": {
      "questIDHigh:4": -1957876484162237390,
      "questIDLow:4": -6996604166554173662
    },
    "5:10": {
      "questIDHigh:4": 8844906862197884825,
      "questIDLow:4": -8759702855720402153
    }
  },
  "properties:10": {
    "betterquesting:10": {
      "autoClaim:1": 0,
      "desc:8": "Craft a Draconic Core!",
      "globalShare:1": 0,
      "icon:10": {
        "Count:3": 1,
        "Damage:2": 0,
        "OreDict:8": "",
        "id:8": "DraconicEvolution:draconicCore"
      },
      "isMain:1": 0,
      "isSilent:1": 0,
      "lockedProgress:1": 0,
      "name:8": "Draconic Core",
      "questLogic:8": "AND",
      "repeatTime:3": -1,
      "repeat_relative:1": 1,
      "simultaneous:1": 0,
      "snd_complete:8": "random.levelup",
      "snd_update:8": "random.levelup",
      "taskLogic:8": "AND",
      "visibility:8": "NORMAL"
    }
  },
  "questIDHigh:4": 8403181620274217470,
  "questIDLow:4": -7465663602975778749,
  "rewards:9": {
    "0:10": {
      "ignoreDisabled:1": 0,
      "index:3": 0,
      "rewardID:8": "bq_standard:item",
      "rewards:9": {
        "0:10": {
          "Count:3": 10,
          "Damage:2": 0,
          "OreDict:8": "",
          "id:8": "DraconicEvolution:draconiumDust"
        }
      }
    }
  },
  "tasks:9": {
    "0:10": {
      "autoConsume:1": 0,
      "consume:1": 0,
      "groupDetect:1": 0,
      "ignoreNBT:1": 1,
      "index:3": 0,
      "partialMatch:1": 1,
      "requiredItems:9": {
        "0:10": {
          "Count:3": 1,
          "Damage:2": 0,
          "OreDict:8": "",
          "id:8": "DraconicEvolution:draconicCore"
        }
      },
      "taskID:8": "bq_standard:retrieval"
    }
  }
}