{
  "preRequisites:9": {
    "0:10": {
      "questIDHigh:4": 5982537112430790484,
      "questIDLow:4": -6636969401397254697
    }
  },
  "properties:10": {
    "betterquesting:10": {
      "autoClaim:1": 0,
      "desc:8": "Craft some Crop Sticks. You can put all types of Seeds on Crop Sticks to turn them into AgriCraft Seeds. The advantage of being an AgriCraft Seed is that you can make the attributes of a Seed better. Each Seed starts with an Attribute of 0/0/0, and you can combine 2 Seeds by planting them diagonally, and placing 2 crop stick on one soil in one of the corners. You can force-grow another plant with bone meal from this soil, that might have better attributes. You can check the Seed\u0027s attributes in the Seed Analyzer, they can go up to 10/10/10, where the Seed will grow much faster, and will produce more fully grown crops. I recommend using this method for most necessary Magical Crops Seeds. Also, FYI, weeds are turned off, and automatic Seed spreading is also turned off.",
      "globalShare:1": 0,
      "icon:10": {
        "Count:3": 1,
        "Damage:2": 0,
        "OreDict:8": "",
        "id:8": "AgriCraft:cropsItem"
      },
      "isMain:1": 0,
      "isSilent:1": 0,
      "lockedProgress:1": 0,
      "name:8": "AgriCraft beginnings",
      "questLogic:8": "AND",
      "repeatTime:3": -1,
      "repeat_relative:1": 1,
      "simultaneous:1": 0,
      "snd_complete:8": "random.levelup",
      "snd_update:8": "random.levelup",
      "taskLogic:8": "AND",
      "visibility:8": "NORMAL"
    }
  },
  "questIDHigh:4": 4202280187781664746,
  "questIDLow:4": -6060698728420680368,
  "rewards:9": {
    "0:10": {
      "choices:9": {
        "0:10": {
          "Count:3": 6,
          "Damage:2": 0,
          "OreDict:8": "",
          "id:8": "minecraft:planks"
        },
        "1:10": {
          "Count:3": 6,
          "Damage:2": 2,
          "OreDict:8": "",
          "id:8": "minecraft:planks"
        },
        "2:10": {
          "Count:3": 6,
          "Damage:2": 1,
          "OreDict:8": "",
          "id:8": "minecraft:planks"
        },
        "3:10": {
          "Count:3": 6,
          "Damage:2": 3,
          "OreDict:8": "",
          "id:8": "minecraft:planks"
        }
      },
      "ignoreDisabled:1": 0,
      "index:3": 0,
      "rewardID:8": "bq_standard:choice"
    }
  },
  "tasks:9": {
    "0:10": {
      "autoConsume:1": 0,
      "consume:1": 0,
      "groupDetect:1": 0,
      "ignoreNBT:1": 1,
      "index:3": 0,
      "partialMatch:1": 1,
      "requiredItems:9": {
        "0:10": {
          "Count:3": 16,
          "Damage:2": 0,
          "OreDict:8": "",
          "id:8": "AgriCraft:cropsItem"
        }
      },
      "taskID:8": "bq_standard:retrieval"
    }
  }
}